django_talar/__init__.py
django_talar/apps.py
django_talar/client.py
django_talar/forms.py
django_talar/serializers.py
django_talar/signals.py
django_talar/urls.py
django_talar/views.py
django_talar/templates/django_talar/make_payment.html
django_talar-1.2.0.dist-info/LICENSE.md
django_talar-1.2.0.dist-info/METADATA
django_talar-1.2.0.dist-info/WHEEL
django_talar-1.2.0.dist-info/top_level.txt
django_talar-1.2.0.dist-info/RECORD
