Metadata-Version: 2.1
Name: django-talar
Version: 1.2.0
Summary: Django app for Talar
Home-page: https://talar.app
Author: Talar
Author-email: hello@talar.app
License: UNKNOWN
Platform: UNKNOWN
Classifier: Programming Language :: Python :: 3
Classifier: License :: OSI Approved :: MIT License
Classifier: Operating System :: OS Independent
License-File: LICENSE.md
Requires-Dist: django (>=2.1)
Requires-Dist: djangorestframework (>=3.9)
Requires-Dist: pyjwt (<1.8,>=1.7)
